darner/__init__.py
darner/config.py
darner/io.py
darner_sdk-0.1.0.dist-info/LICENSE
darner_sdk-0.1.0.dist-info/METADATA
darner_sdk-0.1.0.dist-info/WHEEL
darner_sdk-0.1.0.dist-info/top_level.txt
darner_sdk-0.1.0.dist-info/RECORD
