Metadata-Version: 2.1
Name: darner-sdk
Version: 0.1.0
Summary: A Python SDK for loading and saving data within darner python supports
Home-page: https://github.com/ebottabi/darner
Author: Ebot Tabi
Author-email: ebot.tabi@gmail.com
License: UNKNOWN
Platform: UNKNOWN
Classifier: Development Status :: 3 - Alpha
Classifier: Intended Audience :: Developers
Classifier: License :: OSI Approved :: MIT License
Classifier: Operating System :: OS Independent
Classifier: Programming Language :: Python :: 3
Classifier: Programming Language :: Python :: 3.7
Classifier: Programming Language :: Python :: 3.8
Classifier: Programming Language :: Python :: 3.9
Requires-Python: >=3.7
Requires-Dist: pandas
Requires-Dist: pyarrow
